rebase_dashboard/__init__.py
rebase_dashboard/client.py
rebase_dashboard/components/__init__.py
rebase_dashboard/components/client.py
rebase_dashboard/components/raw_client.py
rebase_dashboard/components/types/__init__.py
rebase_dashboard/components/types/list_components_api_v_1_dashboard_components_get_response_item.py
rebase_dashboard/core/__init__.py
rebase_dashboard/core/api_error.py
rebase_dashboard/core/client_wrapper.py
rebase_dashboard/core/datetime_utils.py
rebase_dashboard/core/file.py
rebase_dashboard/core/force_multipart.py
rebase_dashboard/core/http_client.py
rebase_dashboard/core/http_response.py
rebase_dashboard/core/jsonable_encoder.py
rebase_dashboard/core/pydantic_utilities.py
rebase_dashboard/core/query_encoder.py
rebase_dashboard/core/remove_none_from_dict.py
rebase_dashboard/core/request_options.py
rebase_dashboard/core/serialization.py
rebase_dashboard/dashboards/__init__.py
rebase_dashboard/dashboards/client.py
rebase_dashboard/dashboards/raw_client.py
rebase_dashboard/datasets/__init__.py
rebase_dashboard/datasets/client.py
rebase_dashboard/datasets/raw_client.py
rebase_dashboard/datasets/types/__init__.py
rebase_dashboard/datasets/types/create_geospatial_static_api_v_1_dashboard_datasets_geospatial_static_post_request_geometry_type.py
rebase_dashboard/datasets/types/create_timeseries_live_api_v_1_dashboard_datasets_timeseries_live_post_request_data_format.py
rebase_dashboard/environment.py
rebase_dashboard/errors/__init__.py
rebase_dashboard/errors/unprocessable_entity_error.py
rebase_dashboard/layers/__init__.py
rebase_dashboard/layers/client.py
rebase_dashboard/layers/raw_client.py
rebase_dashboard/layers/types/__init__.py
rebase_dashboard/layers/types/create_layer_api_v_1_dashboard_layers_post_response.py
rebase_dashboard/layers/types/get_layer_api_v_1_dashboard_layers_layer_id_get_response.py
rebase_dashboard/layers/types/list_layers_api_v_1_dashboard_layers_get_response_item.py
rebase_dashboard-0.0.43.dist-info/METADATA
rebase_dashboard-0.0.43.dist-info/WHEEL
rebase_dashboard-0.0.43.dist-info/RECORD
